fastapi_deploy_cli/__init__.py
fastapi_deploy_cli/config.py
fastapi_deploy_cli/env_handler.py
fastapi_deploy_cli/file_operations.py
fastapi_deploy_cli/github_api.py
fastapi_deploy_cli/main.py
fastapi_deploy_cli/utils.py
fastapi_deploy_cli/templates/pip/Dockerfile
fastapi_deploy_cli/templates/pip/deploy-prod.yml
fastapi_deploy_cli/templates/pip/deploy.yml
fastapi_deploy_cli/templates/pip/docker-compose.yml
fastapi_deploy_cli/templates/uv/Dockerfile
fastapi_deploy_cli/templates/uv/deploy-prod.yml
fastapi_deploy_cli/templates/uv/deploy.yml
fastapi_deploy_cli/templates/uv/docker-compose.yml
fastapi_deploy_cli-0.2.0.dist-info/METADATA
fastapi_deploy_cli-0.2.0.dist-info/WHEEL
fastapi_deploy_cli-0.2.0.dist-info/entry_points.txt
fastapi_deploy_cli-0.2.0.dist-info/RECORD
