Metadata-Version: 2.4
Name: fastapi-deploy-cli
Version: 0.2.0
Summary: CLI tool for setting up deployment of FastAPI applications
Author-email: Your Name <your.email@example.com>
License: MIT
Requires-Python: >=3.8
Requires-Dist: build>=1.2.2.post1
Requires-Dist: click>=8.1.8
Requires-Dist: pyyaml>=6.0.2
Requires-Dist: questionary>=2.1.0
Requires-Dist: requests>=2.32.3
Requires-Dist: rich>=14.0.0
Requires-Dist: twine>=6.1.0
